numbr/__init__.py
numbr/engine.py
numbr-2.0.6.dist-info/METADATA
numbr-2.0.6.dist-info/WHEEL
numbr-2.0.6.dist-info/top_level.txt
numbr-2.0.6.dist-info/RECORD
