Metadata-Version: 2.1
Name: numbr
Version: 2.0.6
Summary: A comprehensive Python library for parsing and converting numbers between numeric, word, and ordinal formats.
Home-page: https://github.com/cedricmoorejr/numbr/tree/v2.0.6
Author: Cedric Moore Jr.
Author-email: cedricmoorejunior5@gmail.com
License: MIT
Classifier: Programming Language :: Python :: 3
Classifier: Operating System :: Microsoft :: Windows
Classifier: Operating System :: POSIX :: Linux
Classifier: Operating System :: MacOS :: MacOS X
Classifier: Development Status :: 5 - Production/Stable
Classifier: Intended Audience :: Developers
Classifier: Natural Language :: English
Classifier: License :: OSI Approved :: MIT License
Classifier: Topic :: Software Development :: Libraries :: Python Modules
Classifier: Programming Language :: Python :: 3.8
Classifier: Programming Language :: Python :: 3.9
Classifier: Programming Language :: Python :: 3.10
Requires-Python: >=3.6
